biosamples_v4/__init__.py
biosamples_v4/aap.py
biosamples_v4/api.py
biosamples_v4/convert_functions.py
biosamples_v4/encoders.py
biosamples_v4/exceptions.py
biosamples_v4/filters.py
biosamples_v4/models.py
biosamples_v4/sampletab.py
biosamples_v4/traverson.py
biosamples_v4/utilities.py
biosamples_v4-0.0.5.dist-info/LICENSE.txt
biosamples_v4-0.0.5.dist-info/METADATA
biosamples_v4-0.0.5.dist-info/WHEEL
biosamples_v4-0.0.5.dist-info/top_level.txt
biosamples_v4-0.0.5.dist-info/RECORD
